{
  "project_info": {
    "project_number": "151705258392",
    "firebase_url": "https://docchi-c0f81.firebaseio.com",
    "project_id": "docchi-c0f81",
    "storage_bucket": "docchi-c0f81.appspot.com"
  },
  "client": [
    {
      "client_info": {
        "mobilesdk_app_id": "1:151705258392:android:437905fd0b4438cd2603ed",
        "android_client_info": {
          "package_name": "com.example.docchi"
        }
      },
      "oauth_client": [
        {
          "client_id": "151705258392-1dm79t5uma5lvhfr823cqht15gqcf0dk.apps.googleusercontent.com",
          "client_type": 3
        }
      ],
      "api_key": [
        {
          "current_key": "AIzaSyBCTZnYAkSHvWyqmi8eIXGI6DC1U-xXzuY"
        }
      ],
      "services": {
        "appinvite_service": {
          "other_platform_oauth_client": [
            {
              "client_id": "151705258392-1dm79t5uma5lvhfr823cqht15gqcf0dk.apps.googleusercontent.com",
              "client_type": 3
            }
          ]
        }
      }
    }
  ],
  "configuration_version": "1"
}